torrfetch/__init__.py
torrfetch/core.py
torrfetch/utils.py
torrfetch/sources/__init__.py
torrfetch/sources/pirate_bay.py
torrfetch/sources/yts.py
torrfetch-0.1.4.dist-info/licenses/LICENSE
torrfetch-0.1.4.dist-info/METADATA
torrfetch-0.1.4.dist-info/WHEEL
torrfetch-0.1.4.dist-info/top_level.txt
torrfetch-0.1.4.dist-info/RECORD
