Metadata-Version: 2.4
Name: torrfetch
Version: 0.1.4
Summary: A Python package to fetch torrent metadata from multiple sources
Author-email: Aayush Kumar <aayush214.kumar@gmail.com>
License: MIT
Project-URL: Homepage, https://github.com/aayushkdev/torrfetch
Project-URL: Documentation, https://github.com/aayushkdev/torrfetch#readme
Project-URL: Source, https://github.com/aayushkdev/torrfetch
Project-URL: Tracker, https://github.com/aayushkdev/torrfetch/issues
Keywords: torrent,scraper,metadata,torrent indexer,torrent scraper
Classifier: Programming Language :: Python :: 3
Classifier: License :: OSI Approved :: MIT License
Classifier: Operating System :: OS Independent
Requires-Python: >=3.8
License-File: LICENSE
Requires-Dist: aiohttp
Requires-Dist: beautifulsoup4
Requires-Dist: rapidfuzz
Dynamic: license-file
